src/bmath/Add.py
src/bmath/Decimal.py
src/bmath/Divide.py
src/bmath/Integer.py
src/bmath/Multiply.py
src/bmath/Number.py
src/bmath/Operation.py
src/bmath/Subtract.py
src/bmath/Value.py
src/bmath/__init__.py
stdmath-0.0.1.dist-info/METADATA
stdmath-0.0.1.dist-info/WHEEL
stdmath-0.0.1.dist-info/licenses/LICENSE
stdmath-0.0.1.dist-info/RECORD
