Metadata-Version: 2.1
Name: stdmath
Version: 0.0.1
Summary: A Better Library For Complex Mathematics Based on OOP
Author-email: Rather Not Say <author@example.com>
License-File: LICENSE
Classifier: License :: OSI Approved :: Apache Software License
Classifier: Operating System :: OS Independent
Classifier: Programming Language :: Python :: 3
Requires-Python: >=3.11
